palletdatagenerator/__init__.py
palletdatagenerator/blender_runner.py
palletdatagenerator/cli.py
palletdatagenerator/config.py
palletdatagenerator/generator.py
palletdatagenerator/utils.py
palletdatagenerator/modes/__init__.py
palletdatagenerator/modes/base_generator.py
palletdatagenerator/modes/single_pallet.py
palletdatagenerator/modes/warehouse.py
palletdatagenerator-0.1.3.dist-info/METADATA
palletdatagenerator-0.1.3.dist-info/WHEEL
palletdatagenerator-0.1.3.dist-info/entry_points.txt
palletdatagenerator-0.1.3.dist-info/licenses/LICENSE
palletdatagenerator-0.1.3.dist-info/RECORD
