Metadata-Version: 2.4
Name: palletdatagenerator
Version: 0.1.3
Summary: Professional Blender library for synthetic pallet dataset generation.
Project-URL: Homepage, https://github.com/boubakriibrahim/PalletDataGenerator
Project-URL: Documentation, https://boubakriibrahim.github.io/PalletDataGenerator/
Project-URL: Repository, https://github.com/boubakriibrahim/PalletDataGenerator.git
Project-URL: Issues, https://github.com/boubakriibrahim/PalletDataGenerator/issues
Author-email: Ibrahim Boubakri <ibrahimbouakri1@gmail.com>
License-Expression: MIT
License-File: LICENSE
Keywords: 3d-rendering,blender,computer-vision,dataset-generation,machine-learning,pallet-detection,synthetic-data
Classifier: Development Status :: 2 - Pre-Alpha
Classifier: Intended Audience :: Developers
Classifier: Intended Audience :: Science/Research
Classifier: License :: OSI Approved :: MIT License
Classifier: Operating System :: OS Independent
Classifier: Programming Language :: Python :: 3.11
Classifier: Topic :: Multimedia :: Graphics :: 3D Rendering
Classifier: Topic :: Scientific/Engineering :: Artificial Intelligence
Classifier: Topic :: Scientific/Engineering :: Image Processing
Requires-Python: >=3.11
Requires-Dist: numpy>=1.20.0
Requires-Dist: pascal-voc-writer>=0.1.4
Requires-Dist: pillow>=10.0.0
Requires-Dist: pyyaml>=6.0
Provides-Extra: dev
Requires-Dist: black>=23.0.0; extra == 'dev'
Requires-Dist: mypy>=1.5.0; extra == 'dev'
Requires-Dist: myst-parser>=2.0.0; extra == 'dev'
Requires-Dist: pre-commit>=3.0.0; extra == 'dev'
Requires-Dist: pytest-cov>=4.0.0; extra == 'dev'
Requires-Dist: pytest-mock>=3.10.0; extra == 'dev'
Requires-Dist: pytest>=7.0.0; extra == 'dev'
Requires-Dist: ruff>=0.1.0; extra == 'dev'
Requires-Dist: sphinx-rtd-theme>=1.3.0; extra == 'dev'
Requires-Dist: sphinx>=7.0.0; extra == 'dev'
Provides-Extra: docs
Requires-Dist: linkify-it-py>=2.0.0; extra == 'docs'
Requires-Dist: myst-parser>=2.0.0; extra == 'docs'
Requires-Dist: sphinx-autodoc-typehints>=1.24.0; extra == 'docs'
Requires-Dist: sphinx-copybutton>=0.5.2; extra == 'docs'
Requires-Dist: sphinx-rtd-theme>=1.3.0; extra == 'docs'
Requires-Dist: sphinx>=7.0.0; extra == 'docs'
Requires-Dist: sphinxext-opengraph>=0.8.2; extra == 'docs'
Provides-Extra: test
Requires-Dist: coveralls>=3.3.1; extra == 'test'
Requires-Dist: pytest-cov>=4.0.0; extra == 'test'
Requires-Dist: pytest-mock>=3.10.0; extra == 'test'
Requires-Dist: pytest>=7.0.0; extra == 'test'
